{
  "annotations": [
    {
      "area": 292952.26,
      "bbox": [
        79.87,
        396.14,
        1000.52,
        292.8
      ],
      "category_id": 4,
      "id": 0,
      "image_id": 0,
      "isCrowd": 0,
      "segmentation": [
        [
          79.87,
          396.14,
          1080.39,
          396.14,
          1080.39,
          688.94,
          79.87,
          688.94
        ]
      ]
    },
    {
      "area": 90952.17,
      "bbox": [
        7.17,
        665.98,
        562.44,
        161.71
      ],
      "category_id": 5,
      "id": 1,
      "image_id": 0,
      "isCrowd": 0,
      "segmentation": [
        [
          7.17,
          665.98,
          569.61,
          665.98,
          569.61,
          827.69,
          7.17,
          827.69
        ]
      ]
    },
    {
      "area": 275077.65,
      "bbox": [
        565.78,
        3.83,
        434.26,
        633.44
      ],
      "category_id": 4,
      "id": 2,
      "image_id": 0,
      "isCrowd": 0,
      "segmentation": [
        [
          565.78,
          3.83,
          1000.04,
          3.83,
          1000.04,
          637.27,
          565.78,
          637.27
        ]
      ]
    },
    {
      "area": 65190.3,
      "bbox": [
        121.96,
        116.74,
        247.74,
        263.14
      ],
      "category_id": 5,
      "id": 3,
      "image_id": 0,
      "isCrowd": 0,
      "segmentation": [
        [
          121.96,
          116.74,
          369.7,
          116.74,
          369.7,
          379.88,
          121.96,
          379.88
        ]
      ]
    },
    {
      "area": 24138.78,
      "bbox": [
        857.08,
        1280.28,
        110.48,
        218.49
      ],
      "category_id": 5,
      "id": 4,
      "image_id": 0,
      "isCrowd": 0,
      "segmentation": [
        [
          857.08,
          1280.28,
          967.56,
          1280.28,
          967.56,
          1498.77,
          857.08,
          1498.77
        ]
      ]
    },
    {
      "area": 47004.3,
      "bbox": [
        727.9,
        1212.27,
        181.87,
        258.45
      ],
      "category_id": 5,
      "id": 5,
      "image_id": 0,
      "isCrowd": 0,
      "segmentation": [
        [
          727.9,
          1212.27,
          909.77,
          1212.27,
          909.77,
          1470.72,
          727.9,
          1470.72
        ]
      ]
    },
    {
      "area": 147610.37,
      "bbox": [
        699.01,
        720.88,
        382.44,
        385.97
      ],
      "category_id": 5,
      "id": 6,
      "image_id": 0,
      "isCrowd": 0,
      "segmentation": [
        [
          699.01,
          720.88,
          1081.45,
          720.88,
          1081.45,
          1106.85,
          699.01,
          1106.85
        ]
      ]
    },
    {
      "area": 51960.86,
      "bbox": [
        787.39,
        5.04,
        394.33,
        131.77
      ],
      "category_id": 5,
      "id": 7,
      "image_id": 0,
      "isCrowd": 0,
      "segmentation": [
        [
          787.39,
          5.04,
          1181.72,
          5.04,
          1181.72,
          136.81,
          787.39,
          136.81
        ]
      ]
    },
    {
      "area": 117909.13,
      "bbox": [
        151.7,
        326.4,
        300.85,
        391.92
      ],
      "category_id": 5,
      "id": 8,
      "image_id": 0,
      "isCrowd": 0,
      "segmentation": [
        [
          151.7,
          326.4,
          452.55,
          326.4,
          452.55,
          718.32,
          151.7,
          718.32
        ]
      ]
    },
    {
      "area": 166427.19,
      "bbox": [
        429.03,
        415.69,
        301.75,
        551.54
      ],
      "category_id": 4,
      "id": 20,
      "image_id": 2,
      "isCrowd": 0,
      "segmentation": [
        [
          429.03,
          415.69,
          730.78,
          415.69,
          730.78,
          967.23,
          429.03,
          967.23
        ]
      ]
    },
    {
      "area": 124623.31,
      "bbox": [
        591.07,
        517.7,
        487.4,
        255.69
      ],
      "category_id": 4,
      "id": 21,
      "image_id": 2,
      "isCrowd": 0,
      "segmentation": [
        [
          591.07,
          517.7,
          1078.47,
          517.7,
          1078.47,
          773.39,
          591.07,
          773.39
        ]
      ]
    },
    {
      "area": 140723.93,
      "bbox": [
        708.45,
        38.21,
        350.88,
        401.06
      ],
      "category_id": 4,
      "id": 22,
      "image_id": 2,
      "isCrowd": 0,
      "segmentation": [
        [
          708.45,
          38.21,
          1059.33,
          38.21,
          1059.33,
          439.27,
          708.45,
          439.27
        ]
      ]
    },
    {
      "area": 75195.32,
      "bbox": [
        532.38,
        214.2,
        298.56,
        251.86
      ],
      "category_id": 5,
      "id": 23,
      "image_id": 2,
      "isCrowd": 0,
      "segmentation": [
        [
          532.38,
          214.2,
          830.94,
          214.2,
          830.94,
          466.06,
          532.38,
          466.06
        ]
      ]
    },
    {
      "area": 100922.58,
      "bbox": [
        342.26,
        117.28,
        221.37,
        455.9
      ],
      "category_id": 4,
      "id": 24,
      "image_id": 2,
      "isCrowd": 0,
      "segmentation": [
        [
          342.26,
          117.28,
          563.63,
          117.28,
          563.63,
          573.18,
          342.26,
          573.18
        ]
      ]
    },
    {
      "area": 30536.41,
      "bbox": [
        850.08,
        716.64,
        117.38,
        260.15
      ],
      "category_id": 5,
      "id": 25,
      "image_id": 2,
      "isCrowd": 0,
      "segmentation": [
        [
          850.08,
          716.64,
          967.46,
          716.64,
          967.46,
          976.79,
          850.08,
          976.79
        ]
      ]
    },
    {
      "area": 81631.96,
      "bbox": [
        207.02,
        739.6,
        282.62,
        288.84
      ],
      "category_id": 5,
      "id": 26,
      "image_id": 2,
      "isCrowd": 0,
      "segmentation": [
        [
          207.02,
          739.6,
          489.64,
          739.6,
          489.64,
          1028.44,
          207.02,
          1028.44
        ]
      ]
    },
    {
      "area": 22680.35,
      "bbox": [
        1186.92,
        1082.64,
        200.96,
        112.86
      ],
      "category_id": 5,
      "id": 27,
      "image_id": 2,
      "isCrowd": 0,
      "segmentation": [
        [
          1186.92,
          1082.64,
          1387.88,
          1082.64,
          1387.88,
          1195.5,
          1186.92,
          1195.5
        ]
      ]
    },
    {
      "area": 17596.56,
      "bbox": [
        1394.9,
        434.81,
        152.47,
        115.41
      ],
      "category_id": 5,
      "id": 28,
      "image_id": 2,
      "isCrowd": 0,
      "segmentation": [
        [
          1394.9,
          434.81,
          1547.37,
          434.81,
          1547.37,
          550.22,
          1394.9,
          550.22
        ]
      ]
    },
    {
      "area": 54163.54,
      "bbox": [
        565.55,
        0,
        237.32,
        228.23
      ],
      "category_id": 5,
      "id": 29,
      "image_id": 2,
      "isCrowd": 0,
      "segmentation": [
        [
          565.55,
          0,
          802.87,
          0,
          802.87,
          228.23,
          565.55,
          228.23
        ]
      ]
    },
    {
      "area": 66970.31,
      "bbox": [
        899.84,
        414.41,
        306.22,
        218.7
      ],
      "category_id": 4,
      "id": 30,
      "image_id": 2,
      "isCrowd": 0,
      "segmentation": [
        [
          899.84,
          414.41,
          1206.06,
          414.41,
          1206.06,
          633.11,
          899.84,
          633.11
        ]
      ]
    },
    {
      "area": 38644.43,
      "bbox": [
        1257.1,
        832.69,
        159.49,
        242.3
      ],
      "category_id": 4,
      "id": 31,
      "image_id": 2,
      "isCrowd": 0,
      "segmentation": [
        [
          1257.1,
          832.69,
          1416.59,
          832.69,
          1416.59,
          1074.99,
          1257.1,
          1074.99
        ]
      ]
    },
    {
      "area": 134995.91,
      "bbox": [
        353.97,
        547.45,
        458.92,
        294.16
      ],
      "category_id": 4,
      "id": 49,
      "image_id": 5,
      "isCrowd": 0,
      "segmentation": [
        [
          353.97,
          547.45,
          812.89,
          547.45,
          812.89,
          841.61,
          353.97,
          841.61
        ]
      ]
    },
    {
      "area": 88180.4,
      "bbox": [
        353.97,
        768.49,
        327.2,
        269.5
      ],
      "category_id": 5,
      "id": 50,
      "image_id": 5,
      "isCrowd": 0,
      "segmentation": [
        [
          353.97,
          768.49,
          681.17,
          768.49,
          681.17,
          1037.99,
          353.97,
          1037.99
        ]
      ]
    },
    {
      "area": 23659.95,
      "bbox": [
        97.31,
        1186.77,
        194.62,
        121.57
      ],
      "category_id": 5,
      "id": 51,
      "image_id": 5,
      "isCrowd": 0,
      "segmentation": [
        [
          97.31,
          1186.77,
          291.93,
          1186.77,
          291.93,
          1308.34,
          97.31,
          1308.34
        ]
      ]
    },
    {
      "area": 52492.97,
      "bbox": [
        374.36,
        1448.61,
        346.74,
        151.3900000000001
      ],
      "category_id": 4,
      "id": 52,
      "image_id": 5,
      "isCrowd": 0,
      "segmentation": [
        [
          374.36,
          1448.61,
          721.1,
          1448.61,
          721.1,
          1600,
          374.36,
          1600
        ]
      ]
    },
    {
      "area": 107127.91,
      "bbox": [
        930.17,
        1023.54,
        269.83000000000004,
        397.02
      ],
      "category_id": 5,
      "id": 53,
      "image_id": 5,
      "isCrowd": 0,
      "segmentation": [
        [
          930.17,
          1023.54,
          1200,
          1023.54,
          1200,
          1420.56,
          930.17,
          1420.56
        ]
      ]
    },
    {
      "area": 72277.89,
      "bbox": [
        277.48,
        414.82,
        242.21,
        298.41
      ],
      "category_id": 5,
      "id": 54,
      "image_id": 5,
      "isCrowd": 0,
      "segmentation": [
        [
          277.48,
          414.82,
          519.69,
          414.82,
          519.69,
          713.23,
          277.48,
          713.23
        ]
      ]
    },
    {
      "area": 93113.81,
      "bbox": [
        399.86,
        171.68,
        343.34,
        271.2
      ],
      "category_id": 5,
      "id": 55,
      "image_id": 5,
      "isCrowd": 0,
      "segmentation": [
        [
          399.86,
          171.68,
          743.2,
          171.68,
          743.2,
          442.88,
          399.86,
          442.88
        ]
      ]
    },
    {
      "area": 138909.28,
      "bbox": [
        787.39,
        268.59,
        412.61,
        336.66
      ],
      "category_id": 5,
      "id": 56,
      "image_id": 5,
      "isCrowd": 0,
      "segmentation": [
        [
          787.39,
          268.59,
          1200,
          268.59,
          1200,
          605.25,
          787.39,
          605.25
        ]
      ]
    },
    {
      "area": 100464.51,
      "bbox": [
        547.73,
        754.88,
        309.35,
        324.76
      ],
      "category_id": 5,
      "id": 57,
      "image_id": 5,
      "isCrowd": 0,
      "segmentation": [
        [
          547.73,
          754.88,
          857.08,
          754.88,
          857.08,
          1079.64,
          547.73,
          1079.64
        ]
      ]
    },
    {
      "area": 136114.5,
      "bbox": [
        1196.16,
        668.4,
        293.54,
        463.7
      ],
      "category_id": 4,
      "id": 67,
      "image_id": 7,
      "isCrowd": 0,
      "segmentation": [
        [
          1196.16,
          668.4,
          1489.7,
          668.4,
          1489.7,
          1132.1,
          1196.16,
          1132.1
        ]
      ]
    },
    {
      "area": 84531.33,
      "bbox": [
        201.97,
        145.38,
        274.39,
        308.07
      ],
      "category_id": 5,
      "id": 68,
      "image_id": 7,
      "isCrowd": 0,
      "segmentation": [
        [
          201.97,
          145.38,
          476.36,
          145.38,
          476.36,
          453.45,
          201.97,
          453.45
        ]
      ]
    },
    {
      "area": 122572.57,
      "bbox": [
        14.36,
        586.75,
        404.57,
        302.97
      ],
      "category_id": 4,
      "id": 69,
      "image_id": 7,
      "isCrowd": 0,
      "segmentation": [
        [
          14.36,
          586.75,
          418.93,
          586.75,
          418.93,
          889.72,
          14.36,
          889.72
        ]
      ]
    },
    {
      "area": 78437.41,
      "bbox": [
        319.38,
        721.97,
        281.41,
        278.73
      ],
      "category_id": 4,
      "id": 70,
      "image_id": 7,
      "isCrowd": 0,
      "segmentation": [
        [
          319.38,
          721.97,
          600.79,
          721.97,
          600.79,
          1000.7,
          319.38,
          1000.7
        ]
      ]
    },
    {
      "area": 64765.9,
      "bbox": [
        417.65,
        699.01,
        213.77,
        302.97
      ],
      "category_id": 5,
      "id": 71,
      "image_id": 7,
      "isCrowd": 0,
      "segmentation": [
        [
          417.65,
          699.01,
          631.42,
          699.01,
          631.42,
          1001.98,
          417.65,
          1001.98
        ]
      ]
    },
    {
      "area": 104179.58,
      "bbox": [
        221.11,
        966.9,
        457.53,
        227.7
      ],
      "category_id": 4,
      "id": 72,
      "image_id": 7,
      "isCrowd": 0,
      "segmentation": [
        [
          221.11,
          966.9,
          678.64,
          966.9,
          678.64,
          1194.6,
          221.11,
          1194.6
        ]
      ]
    },
    {
      "area": 121110.18,
      "bbox": [
        660.14,
        478.32,
        310.77,
        389.71
      ],
      "category_id": 5,
      "id": 73,
      "image_id": 7,
      "isCrowd": 0,
      "segmentation": [
        [
          660.14,
          478.32,
          970.91,
          478.32,
          970.91,
          868.03,
          660.14,
          868.03
        ]
      ]
    },
    {
      "area": 117181.77,
      "bbox": [
        22.02,
        176,
        283.96,
        412.67
      ],
      "category_id": 5,
      "id": 74,
      "image_id": 7,
      "isCrowd": 0,
      "segmentation": [
        [
          22.02,
          176,
          305.98,
          176,
          305.98,
          588.67,
          22.02,
          588.67
        ]
      ]
    },
    {
      "area": 132106.58,
      "bbox": [
        700.98,
        36.95,
        500.29,
        264.06
      ],
      "category_id": 4,
      "id": 75,
      "image_id": 7,
      "isCrowd": 0,
      "segmentation": [
        [
          700.98,
          36.95,
          1201.27,
          36.95,
          1201.27,
          301.01,
          700.98,
          301.01
        ]
      ]
    },
    {
      "area": 76221.49,
      "bbox": [
        1274.01,
        177.27,
        175.48,
        434.36
      ],
      "category_id": 4,
      "id": 76,
      "image_id": 7,
      "isCrowd": 0,
      "segmentation": [
        [
          1274.01,
          177.27,
          1449.49,
          177.27,
          1449.49,
          611.63,
          1274.01,
          611.63
        ]
      ]
    },
    {
      "area": 61571.25,
      "bbox": [
        733.52,
        989.5,
        292.5,
        210.5
      ],
      "category_id": 4,
      "id": 77,
      "image_id": 7,
      "isCrowd": 0,
      "segmentation": [
        [
          733.52,
          989.5,
          1026.02,
          989.5,
          1026.02,
          1200,
          733.52,
          1200
        ]
      ]
    },
    {
      "area": 40315.83,
      "bbox": [
        688.26,
        1010.99,
        213.3,
        189.01
      ],
      "category_id": 4,
      "id": 78,
      "image_id": 7,
      "isCrowd": 0,
      "segmentation": [
        [
          688.26,
          1010.99,
          901.56,
          1010.99,
          901.56,
          1200,
          688.26,
          1200
        ]
      ]
    },
    {
      "area": 80298.95,
      "bbox": [
        1127.3,
        0,
        441.3,
        181.96
      ],
      "category_id": 4,
      "id": 79,
      "image_id": 8,
      "isCrowd": 0,
      "segmentation": [
        [
          1127.3,
          0,
          1568.6,
          0,
          1568.6,
          181.96,
          1127.3,
          181.96
        ]
      ]
    },
    {
      "area": 91394.07,
      "bbox": [
        605.66,
        937.47,
        351.34,
        260.13
      ],
      "category_id": 5,
      "id": 80,
      "image_id": 8,
      "isCrowd": 0,
      "segmentation": [
        [
          605.66,
          937.47,
          957,
          937.47,
          957,
          1197.6,
          605.66,
          1197.6
        ]
      ]
    },
    {
      "area": 57809.36,
      "bbox": [
        345.4,
        1022.3,
        325.32,
        177.70000000000005
      ],
      "category_id": 5,
      "id": 81,
      "image_id": 8,
      "isCrowd": 0,
      "segmentation": [
        [
          345.4,
          1022.3,
          670.72,
          1022.3,
          670.72,
          1200,
          345.4,
          1200
        ]
      ]
    },
    {
      "area": 44219.02,
      "bbox": [
        325.04,
        905.81,
        153.32,
        288.41
      ],
      "category_id": 5,
      "id": 82,
      "image_id": 8,
      "isCrowd": 0,
      "segmentation": [
        [
          325.04,
          905.81,
          478.36,
          905.81,
          478.36,
          1194.22,
          325.04,
          1194.22
        ]
      ]
    },
    {
      "area": 78879.34,
      "bbox": [
        713.15,
        352.74,
        351.34,
        224.51
      ],
      "category_id": 5,
      "id": 83,
      "image_id": 8,
      "isCrowd": 0,
      "segmentation": [
        [
          713.15,
          352.74,
          1064.49,
          352.74,
          1064.49,
          577.25,
          713.15,
          577.25
        ]
      ]
    },
    {
      "area": 138195.1,
      "bbox": [
        580.76,
        4.39,
        285.15,
        484.64
      ],
      "category_id": 4,
      "id": 84,
      "image_id": 8,
      "isCrowd": 0,
      "segmentation": [
        [
          580.76,
          4.39,
          865.91,
          4.39,
          865.91,
          489.03,
          580.76,
          489.03
        ]
      ]
    },
    {
      "area": 20197.82,
      "bbox": [
        1474.68,
        839.08,
        125.31999999999994,
        161.17
      ],
      "category_id": 5,
      "id": 85,
      "image_id": 8,
      "isCrowd": 0,
      "segmentation": [
        [
          1474.68,
          839.08,
          1600,
          839.08,
          1600,
          1000.25,
          1474.68,
          1000.25
        ]
      ]
    },
    {
      "area": 97614.43,
      "bbox": [
        833.1,
        7.79,
        245.54,
        397.55
      ],
      "category_id": 4,
      "id": 86,
      "image_id": 8,
      "isCrowd": 0,
      "segmentation": [
        [
          833.1,
          7.79,
          1078.64,
          7.79,
          1078.64,
          405.34,
          833.1,
          405.34
        ]
      ]
    },
    {
      "area": 118158.84,
      "bbox": [
        602.26,
        75.65,
        480.34,
        245.99
      ],
      "category_id": 4,
      "id": 87,
      "image_id": 8,
      "isCrowd": 0,
      "segmentation": [
        [
          602.26,
          75.65,
          1082.6,
          75.65,
          1082.6,
          321.64,
          602.26,
          321.64
        ]
      ]
    },
    {
      "area": 51519.4,
      "bbox": [
        776.52,
        539.36,
        191.8,
        268.61
      ],
      "category_id": 5,
      "id": 88,
      "image_id": 8,
      "isCrowd": 0,
      "segmentation": [
        [
          776.52,
          539.36,
          968.32,
          539.36,
          968.32,
          807.97,
          776.52,
          807.97
        ]
      ]
    },
    {
      "area": 71578.16,
      "bbox": [
        222.07,
        581.21,
        265.35,
        269.75
      ],
      "category_id": 5,
      "id": 89,
      "image_id": 8,
      "isCrowd": 0,
      "segmentation": [
        [
          222.07,
          581.21,
          487.42,
          581.21,
          487.42,
          850.96,
          222.07,
          850.96
        ]
      ]
    },
    {
      "area": 305334,
      "bbox": [
        607.19,
        652.13,
        581.91,
        524.71
      ],
      "category_id": 4,
      "id": 102,
      "image_id": 11,
      "isCrowd": 0,
      "segmentation": [
        [
          607.19,
          652.13,
          1189.1,
          652.13,
          1189.1,
          1176.84,
          607.19,
          1176.84
        ]
      ]
    },
    {
      "area": 96590.15,
      "bbox": [
        315.86,
        988.85,
        381.9,
        252.92
      ],
      "category_id": 5,
      "id": 103,
      "image_id": 11,
      "isCrowd": 0,
      "segmentation": [
        [
          315.86,
          988.85,
          697.76,
          988.85,
          697.76,
          1241.77,
          315.86,
          1241.77
        ]
      ]
    },
    {
      "area": 123065.65,
      "bbox": [
        821.54,
        1203.27,
        310.2,
        396.73
      ],
      "category_id": 4,
      "id": 104,
      "image_id": 11,
      "isCrowd": 0,
      "segmentation": [
        [
          821.54,
          1203.27,
          1131.74,
          1203.27,
          1131.74,
          1600,
          821.54,
          1600
        ]
      ]
    },
    {
      "area": 15244.21,
      "bbox": [
        258.5,
        235.38,
        137.36,
        110.98
      ],
      "category_id": 5,
      "id": 105,
      "image_id": 11,
      "isCrowd": 0,
      "segmentation": [
        [
          258.5,
          235.38,
          395.86,
          235.38,
          395.86,
          346.36,
          258.5,
          346.36
        ]
      ]
    },
    {
      "area": 122213.11,
      "bbox": [
        622.29,
        262.56,
        433.98,
        281.61
      ],
      "category_id": 4,
      "id": 106,
      "image_id": 11,
      "isCrowd": 0,
      "segmentation": [
        [
          622.29,
          262.56,
          1056.27,
          262.56,
          1056.27,
          544.17,
          622.29,
          544.17
        ]
      ]
    },
    {
      "area": 50183.63,
      "bbox": [
        924.19,
        2.84,
        275.80999999999995,
        181.95
      ],
      "category_id": 5,
      "id": 107,
      "image_id": 11,
      "isCrowd": 0,
      "segmentation": [
        [
          924.19,
          2.84,
          1200,
          2.84,
          1200,
          184.79,
          924.19,
          184.79
        ]
      ]
    },
    {
      "area": 28052.88,
      "bbox": [
        329.45,
        30.02,
        205.29,
        136.65
      ],
      "category_id": 5,
      "id": 108,
      "image_id": 11,
      "isCrowd": 0,
      "segmentation": [
        [
          329.45,
          30.02,
          534.74,
          30.02,
          534.74,
          166.67,
          329.45,
          166.67
        ]
      ]
    },
    {
      "area": 230186.93,
      "bbox": [
        472.24,
        1132.34,
        492.21,
        467.6600000000001
      ],
      "category_id": 4,
      "id": 109,
      "image_id": 12,
      "isCrowd": 0,
      "segmentation": [
        [
          472.24,
          1132.34,
          964.45,
          1132.34,
          964.45,
          1600,
          472.24,
          1600
        ]
      ]
    },
    {
      "area": 140702.7,
      "bbox": [
        35.05,
        1191.15,
        359.55,
        391.33
      ],
      "category_id": 4,
      "id": 110,
      "image_id": 12,
      "isCrowd": 0,
      "segmentation": [
        [
          35.05,
          1191.15,
          394.6,
          1191.15,
          394.6,
          1582.48,
          35.05,
          1582.48
        ]
      ]
    },
    {
      "area": 208745.17,
      "bbox": [
        577.76,
        557.79,
        557.04,
        374.74
      ],
      "category_id": 5,
      "id": 111,
      "image_id": 12,
      "isCrowd": 0,
      "segmentation": [
        [
          577.76,
          557.79,
          1134.8,
          557.79,
          1134.8,
          932.53,
          577.76,
          932.53
        ]
      ]
    },
    {
      "area": 118446.88,
      "bbox": [
        54.65,
        1005.67,
        401.76,
        294.82
      ],
      "category_id": 4,
      "id": 112,
      "image_id": 12,
      "isCrowd": 0,
      "segmentation": [
        [
          54.65,
          1005.67,
          456.41,
          1005.67,
          456.41,
          1300.49,
          54.65,
          1300.49
        ]
      ]
    },
    {
      "area": 44971.21,
      "bbox": [
        116.46,
        349.68,
        282.66,
        159.1
      ],
      "category_id": 5,
      "id": 113,
      "image_id": 12,
      "isCrowd": 0,
      "segmentation": [
        [
          116.46,
          349.68,
          399.12,
          349.68,
          399.12,
          508.78,
          116.46,
          508.78
        ]
      ]
    },
    {
      "area": 40775.74,
      "bbox": [
        743.59,
        723.67,
        195.23,
        208.86
      ],
      "category_id": 5,
      "id": 114,
      "image_id": 12,
      "isCrowd": 0,
      "segmentation": [
        [
          743.59,
          723.67,
          938.82,
          723.67,
          938.82,
          932.53,
          743.59,
          932.53
        ]
      ]
    },
    {
      "area": 143018,
      "bbox": [
        781.28,
        762.88,
        418.72,
        341.56
      ],
      "category_id": 5,
      "id": 115,
      "image_id": 12,
      "isCrowd": 0,
      "segmentation": [
        [
          781.28,
          762.88,
          1200,
          762.88,
          1200,
          1104.44,
          781.28,
          1104.44
        ]
      ]
    },
    {
      "area": 38671.34,
      "bbox": [
        0,
        485.4,
        152.64,
        253.35
      ],
      "category_id": 5,
      "id": 116,
      "image_id": 12,
      "isCrowd": 0,
      "segmentation": [
        [
          0,
          485.4,
          152.64,
          485.4,
          152.64,
          738.75,
          0,
          738.75
        ]
      ]
    },
    {
      "area": 222778.05,
      "bbox": [
        473.74,
        1144.4,
        498.24,
        447.13
      ],
      "category_id": 4,
      "id": 117,
      "image_id": 13,
      "isCrowd": 0,
      "segmentation": [
        [
          473.74,
          1144.4,
          971.98,
          1144.4,
          971.98,
          1591.53,
          473.74,
          1591.53
        ]
      ]
    },
    {
      "area": 157234.21,
      "bbox": [
        24.5,
        1046.38,
        400.25,
        392.84
      ],
      "category_id": 4,
      "id": 118,
      "image_id": 13,
      "isCrowd": 0,
      "segmentation": [
        [
          24.5,
          1046.38,
          424.75,
          1046.38,
          424.75,
          1439.22,
          24.5,
          1439.22
        ]
      ]
    },
    {
      "area": 136043.28,
      "bbox": [
        39.57,
        1201.71,
        348.99,
        389.82
      ],
      "category_id": 5,
      "id": 119,
      "image_id": 13,
      "isCrowd": 0,
      "segmentation": [
        [
          39.57,
          1201.71,
          388.56,
          1201.71,
          388.56,
          1591.53,
          39.57,
          1591.53
        ]
      ]
    },
    {
      "area": 46780.29,
      "bbox": [
        775.25,
        666.37,
        171.86,
        272.2
      ],
      "category_id": 5,
      "id": 120,
      "image_id": 13,
      "isCrowd": 0,
      "segmentation": [
        [
          775.25,
          666.37,
          947.11,
          666.37,
          947.11,
          938.57,
          775.25,
          938.57
        ]
      ]
    },
    {
      "area": 197509.18,
      "bbox": [
        598.87,
        583.42,
        541.21,
        364.94
      ],
      "category_id": 5,
      "id": 121,
      "image_id": 13,
      "isCrowd": 0,
      "segmentation": [
        [
          598.87,
          583.42,
          1140.08,
          583.42,
          1140.08,
          948.36,
          598.87,
          948.36
        ]
      ]
    },
    {
      "area": 39189.28,
      "bbox": [
        131.53,
        352.7,
        272.11,
        144.02
      ],
      "category_id": 5,
      "id": 122,
      "image_id": 13,
      "isCrowd": 0,
      "segmentation": [
        [
          131.53,
          352.7,
          403.64,
          352.7,
          403.64,
          496.72,
          131.53,
          496.72
        ]
      ]
    },
    {
      "area": 145716.25,
      "bbox": [
        794.85,
        753.83,
        405.15,
        359.66
      ],
      "category_id": 5,
      "id": 123,
      "image_id": 13,
      "isCrowd": 0,
      "segmentation": [
        [
          794.85,
          753.83,
          1200,
          753.83,
          1200,
          1113.49,
          794.85,
          1113.49
        ]
      ]
    },
    {
      "area": 54235.52,
      "bbox": [
        849.12,
        1179.09,
        350.88,
        154.57
      ],
      "category_id": 5,
      "id": 124,
      "image_id": 13,
      "isCrowd": 0,
      "segmentation": [
        [
          849.12,
          1179.09,
          1200,
          1179.09,
          1200,
          1333.66,
          849.12,
          1333.66
        ]
      ]
    },
    {
      "area": 55903.64,
      "bbox": [
        268.72,
        1388.7,
        264.57,
        211.29999999999995
      ],
      "category_id": 5,
      "id": 125,
      "image_id": 13,
      "isCrowd": 0,
      "segmentation": [
        [
          268.72,
          1388.7,
          533.29,
          1388.7,
          533.29,
          1600,
          268.72,
          1600
        ]
      ]
    },
    {
      "area": 61177.12,
      "bbox": [
        540.08,
        676.92,
        195.98,
        312.16
      ],
      "category_id": 5,
      "id": 132,
      "image_id": 15,
      "isCrowd": 0,
      "segmentation": [
        [
          540.08,
          676.92,
          736.06,
          676.92,
          736.06,
          989.08,
          540.08,
          989.08
        ]
      ]
    },
    {
      "area": 96716.96,
      "bbox": [
        886.81,
        838.28,
        285.68,
        338.55
      ],
      "category_id": 5,
      "id": 133,
      "image_id": 15,
      "isCrowd": 0,
      "segmentation": [
        [
          886.81,
          838.28,
          1172.49,
          838.28,
          1172.49,
          1176.83,
          886.81,
          1176.83
        ]
      ]
    },
    {
      "area": 99340.14,
      "bbox": [
        107.41,
        1103.69,
        342.21,
        290.29
      ],
      "category_id": 4,
      "id": 134,
      "image_id": 15,
      "isCrowd": 0,
      "segmentation": [
        [
          107.41,
          1103.69,
          449.62,
          1103.69,
          449.62,
          1393.98,
          107.41,
          1393.98
        ]
      ]
    },
    {
      "area": 72675.11,
      "bbox": [
        534.05,
        506.52,
        289.45,
        251.08
      ],
      "category_id": 5,
      "id": 135,
      "image_id": 15,
      "isCrowd": 0,
      "segmentation": [
        [
          534.05,
          506.52,
          823.5,
          506.52,
          823.5,
          757.6,
          534.05,
          757.6
        ]
      ]
    },
    {
      "area": 407431.22,
      "bbox": [
        190.33,
        664.86,
        570.6,
        714.04
      ],
      "category_id": 4,
      "id": 136,
      "image_id": 16,
      "isCrowd": 0,
      "segmentation": [
        [
          190.33,
          664.86,
          760.93,
          664.86,
          760.93,
          1378.9,
          190.33,
          1378.9
        ]
      ]
    },
    {
      "area": 102392,
      "bbox": [
        698.37,
        414.53,
        251.01,
        407.92
      ],
      "category_id": 5,
      "id": 137,
      "image_id": 16,
      "isCrowd": 0,
      "segmentation": [
        [
          698.37,
          414.53,
          949.38,
          414.53,
          949.38,
          822.45,
          698.37,
          822.45
        ]
      ]
    },
    {
      "area": 142220.02,
      "bbox": [
        274.75,
        1148.93,
        512.56,
        277.47
      ],
      "category_id": 5,
      "id": 138,
      "image_id": 16,
      "isCrowd": 0,
      "segmentation": [
        [
          274.75,
          1148.93,
          787.31,
          1148.93,
          787.31,
          1426.4,
          274.75,
          1426.4
        ]
      ]
    },
    {
      "area": 71210.08,
      "bbox": [
        125.5,
        897.09,
        159.8,
        445.62
      ],
      "category_id": 4,
      "id": 139,
      "image_id": 16,
      "isCrowd": 0,
      "segmentation": [
        [
          125.5,
          897.09,
          285.3,
          897.09,
          285.3,
          1342.71,
          125.5,
          1342.71
        ]
      ]
    },
    {
      "area": 82858.27,
      "bbox": [
        870.23,
        453.74,
        311.31,
        266.16
      ],
      "category_id": 5,
      "id": 140,
      "image_id": 16,
      "isCrowd": 0,
      "segmentation": [
        [
          870.23,
          453.74,
          1181.54,
          453.74,
          1181.54,
          719.9,
          870.23,
          719.9
        ]
      ]
    },
    {
      "area": 15222.97,
      "bbox": [
        1001.38,
        1418.86,
        88.94,
        171.16
      ],
      "category_id": 5,
      "id": 141,
      "image_id": 16,
      "isCrowd": 0,
      "segmentation": [
        [
          1001.38,
          1418.86,
          1090.32,
          1418.86,
          1090.32,
          1590.02,
          1001.38,
          1590.02
        ]
      ]
    },
    {
      "area": 110493,
      "bbox": [
        597.74,
        889.97,
        359.83,
        307.07
      ],
      "category_id": 5,
      "id": 142,
      "image_id": 17,
      "isCrowd": 0,
      "segmentation": [
        [
          597.74,
          889.97,
          957.57,
          889.97,
          957.57,
          1197.04,
          597.74,
          1197.04
        ]
      ]
    },
    {
      "area": 112732.16,
      "bbox": [
        2.55,
        260,
        258.56,
        436
      ],
      "category_id": 4,
      "id": 143,
      "image_id": 17,
      "isCrowd": 0,
      "segmentation": [
        [
          2.55,
          260,
          261.11,
          260,
          261.11,
          696,
          2.55,
          696
        ]
      ]
    },
    {
      "area": 24883.22,
      "bbox": [
        826.31,
        781.39,
        114.29,
        217.72
      ],
      "category_id": 5,
      "id": 144,
      "image_id": 17,
      "isCrowd": 0,
      "segmentation": [
        [
          826.31,
          781.39,
          940.6,
          781.39,
          940.6,
          999.11,
          826.31,
          999.11
        ]
      ]
    },
    {
      "area": 44454.19,
      "bbox": [
        607.92,
        2.13,
        266.48,
        166.82
      ],
      "category_id": 5,
      "id": 145,
      "image_id": 17,
      "isCrowd": 0,
      "segmentation": [
        [
          607.92,
          2.13,
          874.4,
          2.13,
          874.4,
          168.95,
          607.92,
          168.95
        ]
      ]
    },
    {
      "area": 57921.4,
      "bbox": [
        139.46,
        145.77,
        218.39,
        265.22
      ],
      "category_id": 5,
      "id": 146,
      "image_id": 18,
      "isCrowd": 0,
      "segmentation": [
        [
          139.46,
          145.77,
          357.85,
          145.77,
          357.85,
          410.99,
          139.46,
          410.99
        ]
      ]
    },
    {
      "area": 111981.59,
      "bbox": [
        2.55,
        217.02,
        252.9,
        442.79
      ],
      "category_id": 5,
      "id": 147,
      "image_id": 18,
      "isCrowd": 0,
      "segmentation": [
        [
          2.55,
          217.02,
          255.45,
          217.02,
          255.45,
          659.81,
          2.55,
          659.81
        ]
      ]
    },
    {
      "area": 73557.83,
      "bbox": [
        567.19,
        850.39,
        222.35,
        330.82
      ],
      "category_id": 5,
      "id": 148,
      "image_id": 18,
      "isCrowd": 0,
      "segmentation": [
        [
          567.19,
          850.39,
          789.54,
          850.39,
          789.54,
          1181.21,
          567.19,
          1181.21
        ]
      ]
    },
    {
      "area": 26821.67,
      "bbox": [
        1078.64,
        785.92,
        93.92,
        285.58
      ],
      "category_id": 5,
      "id": 149,
      "image_id": 18,
      "isCrowd": 0,
      "segmentation": [
        [
          1078.64,
          785.92,
          1172.56,
          785.92,
          1172.56,
          1071.5,
          1078.64,
          1071.5
        ]
      ]
    },
    {
      "area": 0,
      "bbox": [
        1346.82,
        559.72,
        0,
        0
      ],
      "category_id": 5,
      "id": 150,
      "image_id": 18,
      "isCrowd": 0,
      "segmentation": [
        [
          1346.82,
          559.72,
          1346.82,
          559.72,
          1346.82,
          559.72,
          1346.82,
          559.72
        ]
      ]
    },
    {
      "area": 50022.65,
      "bbox": [
        1058.27,
        381.02,
        299.86,
        166.82
      ],
      "category_id": 5,
      "id": 151,
      "image_id": 18,
      "isCrowd": 0,
      "segmentation": [
        [
          1058.27,
          381.02,
          1358.13,
          381.02,
          1358.13,
          547.84,
          1058.27,
          547.84
        ]
      ]
    },
    {
      "area": 119883.17,
      "bbox": [
        1179.35,
        0,
        310.04,
        386.67
      ],
      "category_id": 5,
      "id": 152,
      "image_id": 18,
      "isCrowd": 0,
      "segmentation": [
        [
          1179.35,
          0,
          1489.39,
          0,
          1489.39,
          386.67,
          1179.35,
          386.67
        ]
      ]
    },
    {
      "area": 55291.65,
      "bbox": [
        561.53,
        702.22,
        158.98,
        347.79
      ],
      "category_id": 5,
      "id": 153,
      "image_id": 18,
      "isCrowd": 0,
      "segmentation": [
        [
          561.53,
          702.22,
          720.51,
          702.22,
          720.51,
          1050.01,
          561.53,
          1050.01
        ]
      ]
    },
    {
      "area": 127853.3,
      "bbox": [
        342.01,
        695.44,
        334.94,
        381.72
      ],
      "category_id": 4,
      "id": 154,
      "image_id": 18,
      "isCrowd": 0,
      "segmentation": [
        [
          342.01,
          695.44,
          676.95,
          695.44,
          676.95,
          1077.16,
          342.01,
          1077.16
        ]
      ]
    },
    {
      "area": 125133.07,
      "bbox": [
        252.62,
        341.43,
        320.23,
        390.76
      ],
      "category_id": 4,
      "id": 155,
      "image_id": 18,
      "isCrowd": 0,
      "segmentation": [
        [
          252.62,
          341.43,
          572.85,
          341.43,
          572.85,
          732.19,
          252.62,
          732.19
        ]
      ]
    },
    {
      "area": 21459.15,
      "bbox": [
        811.6,
        745.2,
        107.5,
        199.62
      ],
      "category_id": 5,
      "id": 156,
      "image_id": 18,
      "isCrowd": 0,
      "segmentation": [
        [
          811.6,
          745.2,
          919.1,
          745.2,
          919.1,
          944.82,
          811.6,
          944.82
        ]
      ]
    },
    {
      "area": 380125.26,
      "bbox": [
        221.98,
        684.46,
        584.17,
        650.71
      ],
      "category_id": 4,
      "id": 181,
      "image_id": 22,
      "isCrowd": 0,
      "segmentation": [
        [
          221.98,
          684.46,
          806.15,
          684.46,
          806.15,
          1335.17,
          221.98,
          1335.17
        ]
      ]
    },
    {
      "area": 144118.92,
      "bbox": [
        285.3,
        1164.01,
        511.06,
        282
      ],
      "category_id": 5,
      "id": 182,
      "image_id": 22,
      "isCrowd": 0,
      "segmentation": [
        [
          285.3,
          1164.01,
          796.36,
          1164.01,
          796.36,
          1446.01,
          285.3,
          1446.01
        ]
      ]
    },
    {
      "area": 101399.3,
      "bbox": [
        720.98,
        458.26,
        249.5,
        406.41
      ],
      "category_id": 5,
      "id": 183,
      "image_id": 22,
      "isCrowd": 0,
      "segmentation": [
        [
          720.98,
          458.26,
          970.48,
          458.26,
          970.48,
          864.67,
          720.98,
          864.67
        ]
      ]
    },
    {
      "area": 93066.77,
      "bbox": [
        404.4,
        428.1,
        281.16,
        331.01
      ],
      "category_id": 4,
      "id": 184,
      "image_id": 23,
      "isCrowd": 0,
      "segmentation": [
        [
          404.4,
          428.1,
          685.56,
          428.1,
          685.56,
          759.11,
          404.4,
          759.11
        ]
      ]
    },
    {
      "area": 164199.1,
      "bbox": [
        12.44,
        1177.58,
        405.53,
        404.9
      ],
      "category_id": 5,
      "id": 185,
      "image_id": 23,
      "isCrowd": 0,
      "segmentation": [
        [
          12.44,
          1177.58,
          417.97,
          1177.58,
          417.97,
          1582.48,
          12.44,
          1582.48
        ]
      ]
    },
    {
      "area": 78172.15,
      "bbox": [
        56.16,
        194.36,
        258.54,
        302.36
      ],
      "category_id": 5,
      "id": 186,
      "image_id": 23,
      "isCrowd": 0,
      "segmentation": [
        [
          56.16,
          194.36,
          314.7,
          194.36,
          314.7,
          496.72,
          56.16,
          496.72
        ]
      ]
    },
    {
      "area": 97049.54,
      "bbox": [
        202.39,
        722.16,
        267.59,
        362.68
      ],
      "category_id": 4,
      "id": 187,
      "image_id": 23,
      "isCrowd": 0,
      "segmentation": [
        [
          202.39,
          722.16,
          469.98,
          722.16,
          469.98,
          1084.84,
          202.39,
          1084.84
        ]
      ]
    },
    {
      "area": 42801.88,
      "bbox": [
        541.58,
        1093.13,
        202.01,
        211.88
      ],
      "category_id": 5,
      "id": 188,
      "image_id": 23,
      "isCrowd": 0,
      "segmentation": [
        [
          541.58,
          1093.13,
          743.59,
          1093.13,
          743.59,
          1305.01,
          541.58,
          1305.01
        ]
      ]
    },
    {
      "area": 120813.59,
      "bbox": [
        99.87,
        1347.99,
        479.4,
        252.01
      ],
      "category_id": 4,
      "id": 189,
      "image_id": 23,
      "isCrowd": 0,
      "segmentation": [
        [
          99.87,
          1347.99,
          579.27,
          1347.99,
          579.27,
          1600,
          99.87,
          1600
        ]
      ]
    },
    {
      "area": 50785.02,
      "bbox": [
        755.65,
        1310.29,
        348.99,
        145.52
      ],
      "category_id": 5,
      "id": 190,
      "image_id": 23,
      "isCrowd": 0,
      "segmentation": [
        [
          755.65,
          1310.29,
          1104.64,
          1310.29,
          1104.64,
          1455.81,
          755.65,
          1455.81
        ]
      ]
    },
    {
      "area": 47400.84,
      "bbox": [
        969.72,
        643.74,
        230.27999999999997,
        205.84
      ],
      "category_id": 5,
      "id": 191,
      "image_id": 23,
      "isCrowd": 0,
      "segmentation": [
        [
          969.72,
          643.74,
          1200,
          643.74,
          1200,
          849.58,
          969.72,
          849.58
        ]
      ]
    },
    {
      "area": 11919.66,
      "bbox": [
        381.78,
        903.12,
        147.74,
        80.68
      ],
      "category_id": 5,
      "id": 192,
      "image_id": 23,
      "isCrowd": 0,
      "segmentation": [
        [
          381.78,
          903.12,
          529.52,
          903.12,
          529.52,
          983.8,
          381.78,
          983.8
        ]
      ]
    },
    {
      "area": 114511.39,
      "bbox": [
        131.54,
        589.12,
        378.5,
        302.54
      ],
      "category_id": 4,
      "id": 199,
      "image_id": 25,
      "isCrowd": 0,
      "segmentation": [
        [
          131.54,
          589.12,
          510.04,
          589.12,
          510.04,
          891.66,
          131.54,
          891.66
        ]
      ]
    },
    {
      "area": 31266.82,
      "bbox": [
        970.01,
        658.11,
        164.07,
        190.57
      ],
      "category_id": 5,
      "id": 200,
      "image_id": 25,
      "isCrowd": 0,
      "segmentation": [
        [
          970.01,
          658.11,
          1134.08,
          658.11,
          1134.08,
          848.68,
          970.01,
          848.68
        ]
      ]
    },
    {
      "area": 80038.41,
      "bbox": [
        1135.22,
        379.89,
        308.35,
        259.57
      ],
      "category_id": 5,
      "id": 201,
      "image_id": 25,
      "isCrowd": 0,
      "segmentation": [
        [
          1135.22,
          379.89,
          1443.57,
          379.89,
          1443.57,
          639.46,
          1135.22,
          639.46
        ]
      ]
    },
    {
      "area": 21314.1,
      "bbox": [
        368.03,
        171.78,
        122.77,
        173.61
      ],
      "category_id": 4,
      "id": 202,
      "image_id": 25,
      "isCrowd": 0,
      "segmentation": [
        [
          368.03,
          171.78,
          490.8,
          171.78,
          490.8,
          345.39,
          368.03,
          345.39
        ]
      ]
    },
    {
      "area": 82805.81,
      "bbox": [
        192.64,
        869.61,
        381.33,
        217.15
      ],
      "category_id": 5,
      "id": 203,
      "image_id": 25,
      "isCrowd": 0,
      "segmentation": [
        [
          192.64,
          869.61,
          573.97,
          869.61,
          573.97,
          1086.76,
          192.64,
          1086.76
        ]
      ]
    },
    {
      "area": 59347.26,
      "bbox": [
        1354.74,
        666.03,
        184.44,
        321.77
      ],
      "category_id": 5,
      "id": 204,
      "image_id": 25,
      "isCrowd": 0,
      "segmentation": [
        [
          1354.74,
          666.03,
          1539.18,
          666.03,
          1539.18,
          987.8,
          1354.74,
          987.8
        ]
      ]
    }
  ],
  "categories": [
    {
      "id": 0,
      "name": "dolphin",
      "supercategory": "none"
    },
    {
      "id": 1,
      "name": "chicken",
      "supercategory": "none"
    },
    {
      "id": 2,
      "name": "cat",
      "supercategory": "none"
    },
    {
      "id": 3,
      "name": "dog",
      "supercategory": "none"
    },
    {
      "id": 4,
      "name": "bad",
      "supercategory": "none"
    },
    {
      "id": 5,
      "name": "good",
      "supercategory": "none"
    }
  ],
  "images": [
    {
      "date_captured": "",
      "file_name": "WhatsApp Image 2022-12-21 at 12.53.01(1).jpeg",
      "height": 1200,
      "id": 25,
      "license": 1,
      "width": 1600
    },
    {
      "date_captured": "",
      "file_name": "WhatsApp Image 2022-12-21 at 12.53.06.jpeg",
      "height": 1600,
      "id": 12,
      "license": 1,
      "width": 1200
    },
    {
      "date_captured": "",
      "file_name": "WhatsApp Image 2022-12-21 at 12.53.09.jpeg",
      "height": 1600,
      "id": 23,
      "license": 1,
      "width": 1200
    },
    {
      "date_captured": "",
      "file_name": "WhatsApp Image 2022-12-21 at 12.53.09(1).jpeg",
      "height": 1600,
      "id": 16,
      "license": 1,
      "width": 1200
    },
    {
      "date_captured": "",
      "file_name": "WhatsApp Image 2022-12-21 at 12.53.05(2).jpeg",
      "height": 1200,
      "id": 2,
      "license": 1,
      "width": 1600
    },
    {
      "date_captured": "",
      "file_name": "WhatsApp Image 2022-12-21 at 12.53.10.jpeg",
      "height": 1600,
      "id": 22,
      "license": 1,
      "width": 1200
    },
    {
      "date_captured": "",
      "file_name": "WhatsApp Image 2022-12-21 at 12.53.11(1).jpeg",
      "height": 1600,
      "id": 11,
      "license": 1,
      "width": 1200
    },
    {
      "date_captured": "",
      "file_name": "WhatsApp Image 2022-12-21 at 12.53.12(1).jpeg",
      "height": 1600,
      "id": 0,
      "license": 1,
      "width": 1200
    },
    {
      "date_captured": "",
      "file_name": "WhatsApp Image 2022-12-21 at 12.53.04.jpeg",
      "height": 1600,
      "id": 5,
      "license": 1,
      "width": 1200
    },
    {
      "date_captured": "",
      "file_name": "WhatsApp Image 2022-12-21 at 12.53.04(1).jpeg",
      "height": 1600,
      "id": 15,
      "license": 1,
      "width": 1200
    },
    {
      "date_captured": "",
      "file_name": "WhatsApp Image 2022-12-21 at 12.52.59.jpeg",
      "height": 1200,
      "id": 8,
      "license": 1,
      "width": 1600
    },
    {
      "date_captured": "",
      "file_name": "WhatsApp Image 2022-12-21 at 12.53.02(5).jpeg",
      "height": 1200,
      "id": 18,
      "license": 1,
      "width": 1600
    },
    {
      "date_captured": "",
      "file_name": "WhatsApp Image 2022-12-21 at 12.53.08.jpeg",
      "height": 1200,
      "id": 7,
      "license": 1,
      "width": 1600
    },
    {
      "date_captured": "",
      "file_name": "WhatsApp Image 2022-12-21 at 12.53.03(1).jpeg",
      "height": 1200,
      "id": 17,
      "license": 1,
      "width": 1600
    },
    {
      "date_captured": "",
      "file_name": "WhatsApp Image 2022-12-21 at 12.53.05(3).jpeg",
      "height": 1600,
      "id": 13,
      "license": 1,
      "width": 1200
    }
  ],
  "info": {},
  "licenses": [
    {
      "id": 1,
      "name": "Unknown",
      "url": ""
    }
  ]
}